TSVPrep/__init__.py
TSVPrep/prep.py
lib/__init__.py
lib/locate.py
lib/prep.py
lib/preprocess.py
testing/__init__.py
tsvprep/__init__.py
tsvprep/locate.py
tsvprep/preprocess.py
TSVPrep-0.2.0.dist-info/LICENSE
TSVPrep-0.2.0.dist-info/METADATA
TSVPrep-0.2.0.dist-info/WHEEL
TSVPrep-0.2.0.dist-info/top_level.txt
TSVPrep-0.2.0.dist-info/RECORD
