Metadata-Version: 2.1
Name: TSVPrep
Version: 0.2.0
Summary: Module for locating and proofreading .tsv files.
Home-page: https://github.com/learnsometing/TSVPrep
Author: Brian Monaccio
Author-email: brianmonaccio@gmail.com
License: UNKNOWN
Platform: UNKNOWN
Classifier: Intended Audience :: Developers
Classifier: Programming Language :: Python :: 3.8
Classifier: License :: OSI Approved :: MIT License
Classifier: Operating System :: OS Independent
Requires-Python: >=3.8
